herepy/__init__.py
herepy/destination_weather_api.py
herepy/error.py
herepy/ev_charging_stations_api.py
herepy/fleet_telematics_api.py
herepy/geocoder_api.py
herepy/geocoder_autocomplete_api.py
herepy/geocoder_reverse_api.py
herepy/here_api.py
herepy/here_enum.py
herepy/isoline_routing_api.py
herepy/map_image_api.py
herepy/map_tile_api.py
herepy/mercator_projection.py
herepy/models.py
herepy/objects.py
herepy/places_api.py
herepy/polling.py
herepy/public_transit_api.py
herepy/py.typed
herepy/rme_api.py
herepy/routing_api.py
herepy/traffic_api.py
herepy/utils.py
herepy/vector_tile_api.py
herepy/platform/__init__.py
herepy/platform/tour_planning_api.py
herepy-3.6.5.dist-info/COPYING
herepy-3.6.5.dist-info/LICENSE
herepy-3.6.5.dist-info/METADATA
herepy-3.6.5.dist-info/NOTICE
herepy-3.6.5.dist-info/WHEEL
herepy-3.6.5.dist-info/top_level.txt
herepy-3.6.5.dist-info/RECORD
