Metadata-Version: 2.1
Name: herepy
Version: 3.6.5
Summary: A library that provides a Python interface to the HERE APIs
Home-page: https://github.com/abdullahselek/HerePy
Download-URL: https://pypi.org/pypi/herepy
Author: Abdullah Selek
Author-email: abdullahselek.os@gmail.com
Maintainer: Abdullah Selek
Maintainer-email: abdullahselek.os@gmail.com
License: MIT License
Keywords: here api,here technologies,here python api clients,rest api clients
Platform: Any
Classifier: Intended Audience :: Developers
Classifier: License :: OSI Approved :: MIT License
Classifier: Operating System :: OS Independent
Classifier: Topic :: Software Development :: Libraries :: Python Modules
Classifier: Programming Language :: Python
Classifier: Programming Language :: Python :: 3
Classifier: Programming Language :: Python :: 3.8
Classifier: Programming Language :: Python :: 3.9
Classifier: Programming Language :: Python :: 3.10
Classifier: Programming Language :: Python :: 3.11
Classifier: Programming Language :: Python :: 3.12
Requires-Python: >=3.8
License-File: LICENSE
License-File: COPYING
License-File: NOTICE
Requires-Dist: Requests<3,>=2.25.1
